linkweaver.py
linkweaver-0.5.0.dist-info/licenses/LICENSE
linkweaver-0.5.0.dist-info/METADATA
linkweaver-0.5.0.dist-info/WHEEL
linkweaver-0.5.0.dist-info/entry_points.txt
linkweaver-0.5.0.dist-info/top_level.txt
linkweaver-0.5.0.dist-info/RECORD
