Metadata-Version: 2.4
Name: linkweaver
Version: 0.5.0
Summary: Extract URLs from markdown files and convert them to individual markdown documents.
Author-email: David Gasquez <davidgasquez@gmail.com>
Requires-Python: >=3.13
License-File: LICENSE
Requires-Dist: markitdown[audio-transcription,pdf,youtube-transcription]>=0.1.2
Dynamic: license-file
